{"__schema":{"queryType":{"name":"RootQuery"},"mutationType":{"name":"RootMutation"},"subscriptionType":null,"types":[{"kind":"INTERFACE","name":"Node","description":"An object with an ID","fields":[{"name":"id","description":"The id of the object","args":[],"type":{"kind":"NON_NULL","name":null,"ofType":{"kind":"SCALAR","name":"ID","ofType":null}},"isDeprecated":false,"deprecationReason":null}],"inputFields":null,"interfaces":null,"enumValues":null,"possibleTypes":[{"kind":"OBJECT","name":"Category","ofType":null},{"kind":"OBJECT","name":"Taxonomy","ofType":null},{"kind":"OBJECT","name":"PostType","ofType":null},{"kind":"OBJECT","name":"Post","ofType":null},{"kind":"OBJECT","name":"Page","ofType":null},{"kind":"OBJECT","name":"User","ofType":null},{"kind":"OBJECT","name":"Comment","ofType":null},{"kind":"OBJECT","name":"CommentAuthor","ofType":null},{"kind":"OBJECT","name":"MediaItem","ofType":null},{"kind":"OBJECT","name":"Tag","ofType":null},{"kind":"OBJECT","name":"Revision","ofType":null},{"kind":"OBJECT","name":"Plugin","ofType":null},{"kind":"OBJECT","name":"Theme","ofType":null}]},{"kind":"UNION","name":"PostObjectUnion","description":null,"fields":null,"inputFields":null,"interfaces":null,"enumValues":null,"possibleTypes":[{"kind":"OBJECT","name":"Post","ofType":null},{"kind":"OBJECT","name":"Page","ofType":null},{"kind":"OBJECT","name":"MediaItem","ofType":null},{"kind":"OBJECT","name":"Revision","ofType":null}]},{"kind":"UNION","name":"CommentAuthorUnion","description":null,"fields":null,"inputFields":null,"interfaces":null,"enumValues":null,"possibleTypes":[{"kind":"OBJECT","name":"User","ofType":null},{"kind":"OBJECT","name":"CommentAuthor","ofType":null}]},{"kind":"UNION","name":"TermObjectUnion","description":null,"fields":null,"inputFields":null,"interfaces":null,"enumValues":null,"possibleTypes":[{"kind":"OBJECT","name":"Category","ofType":null},{"kind":"OBJECT","name":"Tag","ofType":null}]},{"kind":"UNION","name":"MenuItemObjectUnion","description":null,"fields":null,"inputFields":null,"interfaces":null,"enumValues":null,"possibleTypes":[{"kind":"OBJECT","name":"Post","ofType":null},{"kind":"OBJECT","name":"Page","ofType":null},{"kind":"OBJECT","name":"Category","ofType":null},{"kind":"OBJECT","name":"Tag","ofType":null},{"kind":"OBJECT","name":"MenuItem","ofType":null}]}],"directives":[{"name":"include","description":"Directs the executor to include this field or fragment only when the `if` argument is true.","locations":["FIELD","FRAGMENT_SPREAD","INLINE_FRAGMENT"],"args":[{"name":"if","description":"Included when true.","type":{"kind":"NON_NULL","name":null,"ofType":{"kind":"SCALAR","name":"Boolean","ofType":null}},"defaultValue":null}]},{"name":"skip","description":"Directs the executor to skip this field or fragment when the `if` argument is true.","locations":["FIELD","FRAGMENT_SPREAD","INLINE_FRAGMENT"],"args":[{"name":"if","description":"Skipped when true.","type":{"kind":"NON_NULL","name":null,"ofType":{"kind":"SCALAR","name":"Boolean","ofType":null}},"defaultValue":null}]},{"name":"deprecated","description":"Marks an element of a GraphQL schema as no longer supported.","locations":["FIELD_DEFINITION","ENUM_VALUE"],"args":[{"name":"reason","description":"Explains why this element was deprecated, usually also including a suggestion for how to access supported similar data. Formatted in [Markdown](https://daringfireball.net/projects/markdown/).","type":{"kind":"SCALAR","name":"String","ofType":null},"defaultValue":"\"No longer supported\""}]}]}}